<?xml version="1.0" encoding="UTF-8" ?> 
<!DOCTYPE struts-config PUBLIC 
"-//Apache Software Foundation//DTD Struts Configuration 1.1//EN" 
"http://jakarta.apache.org/struts/dtds/struts-config_1_1.dtd"> 
<struts-config>

<form-beans>
<form-bean name="idcodeUploadForm" type="com.winsafe.drp.dao.IdcodeUploadForm"/>
<form-bean name="imgUploadForm" type="com.winsafe.drp.dao.ImgUploadForm"/>
</form-beans>

<action-mappings>

<!-- 手机APP隐私声明版本号验证 -->  
<action path="/phone/checkPrivacyPolicyAction" type="com.winsafe.drp.action.phone.CheckPrivacyPolicyAction"></action>

<!-- 手机登入 -->  
<action path="/phone/loginAction" type="com.winsafe.drp.action.phone.LoginAction">
</action>

<!-- 手机产品验证查询  -->
<action path="/phone/queryFWIdcodeAction" type="com.winsafe.drp.action.phone.QueryFWIdcodeAction">
</action>

<!--手机产品追溯查询  -->
<action path="/phone/queryWlmIdcodeAction" type="com.winsafe.drp.action.phone.QueryWlmIdcodeAction">
</action>

<!--提交产品追溯查询申请  -->
<action path="/phone/applyWlmIdcodeAction" type="com.winsafe.drp.action.phone.ApplyWlmIdcodeAction">
</action>

<!--公告  -->
<action path="/phone/queryAfficheAction" type="com.winsafe.drp.action.phone.QueryAfficheAction">
</action>

<!--投诉建议 -->
<action path="/phone/addSuggestionAction" type="com.winsafe.drp.action.phone.AddSuggestionAction">
</action>

<!--用户注册 -->
<action path="/phone/registerAction" type="com.winsafe.drp.action.phone.RegisterAction">
</action>

<!--发送验证码 -->
<action path="/phone/checkMessageAction" type="com.winsafe.drp.action.phone.CheckMessageAction">
</action>

<!--找回密码 -->
<action path="/phone/getPwdBackAction" type="com.winsafe.drp.action.phone.GetPwdBackAction">
</action>

<!-- 会员登入 -->
<action path="/phone/memberLoginAction" type="com.winsafe.drp.action.phone.MemberLoginAction">
</action>

<action name="idcodeUploadForm" path="/phone/uploadIdcodeAction" type="com.winsafe.drp.keyretailer.action.phone.UploadIdcodeAction">
</action>

<!-- RI用户登入 -->
<action path="/phone/userLoginAction" type="com.winsafe.drp.keyretailer.action.phone.LoginAction">
</action>

<action path="/phone/queryBillReceiveAction" type="com.winsafe.drp.keyretailer.action.phone.QueryBillReceiveAction">
</action>

<action path="/phone/queryBillReceiveIdcodeAction" type="com.winsafe.drp.keyretailer.action.phone.QueryBillReceiveIdcodeAction">
</action>

<action path="/phone/delBillReceiveIdcodeAction" type="com.winsafe.drp.keyretailer.action.phone.DelBillReceiveIdcodeAction">
</action>

<action path="/phone/completeBillReceiveAction" type="com.winsafe.drp.keyretailer.action.phone.CompleteStockAlterMoveReceiveAction">
</action>

<action path="/phone/queryBonusAction" type="com.winsafe.drp.keyretailer.action.phone.QueryBonusAction">
</action>

<action path="/phone/addOrganAction" type="com.winsafe.drp.keyretailer.action.phone.AddOrganAction">
</action>

<action path="/phone/queryOrganAction" type="com.winsafe.drp.keyretailer.action.phone.QueryOrganAction">
</action>

<action path="/phone/queryBonusDetailAction" type="com.winsafe.drp.keyretailer.action.phone.QueryBonusDetailAction">
</action>

<action path="/phone/queryBonusTargetAction" type="com.winsafe.drp.keyretailer.action.phone.QueryBonusTargetAction">
</action>

<action path="/phone/queryOrganAfficheAction" type="com.winsafe.drp.keyretailer.action.phone.QueryAfficheAction">
</action>

<action path="/phone/queryNotReadOrganAfficheAction" type="com.winsafe.drp.keyretailer.action.phone.QueryNotReadAfficheAction">
</action>

<action path="/phone/dealReadOrganAfficheAction" type="com.winsafe.drp.keyretailer.action.phone.DealReadAfficheAction">
</action>

<action path="/phone/queryProductAction" type="com.winsafe.drp.keyretailer.action.phone.QueryProductAction">
</action>

<action path="/phone/queryIdcodeUploadLog" type="com.winsafe.drp.keyretailer.action.phone.QueryIdcodeUploadLog">
</action>

<action path="/phone/queryBonusTargetDetailAction" type="com.winsafe.drp.keyretailer.action.phone.QueryBonusTargetDetailAction">
</action>

<action path="/phone/queryNewPassword" type="com.winsafe.drp.keyretailer.action.phone.QueryNewPasswordAction">
</action>

<action path="/phone/updPasswordAction" type="com.winsafe.drp.keyretailer.action.phone.UpdPasswordAction">
</action>

<action path="/phone/updMobileAction" type="com.winsafe.drp.keyretailer.action.phone.UpdMobileAction">
</action>

<action path="/phone/countBillReceiveAction" type="com.winsafe.drp.keyretailer.action.phone.CountBillReceiveAction">
</action>

<action path="/phone/dealbackproiftAction" type="com.winsafe.drp.keyretailer.action.phone.DealBackpRroiftAction">
</action>

<action name="imgUploadForm" path="/phone/uploadUserImgAction" type="com.winsafe.drp.keyretailer.action.phone.UploadUserImgAction">
</action>
<!--获取验证码-->  
<action path="/phone/getIdentifyCodeAction" type="com.winsafe.drp.keyretailer.action.phone.GetIdentifyCodeAction">
</action>

<action path="/phone/updAfficeToReadAction" type="com.winsafe.drp.keyretailer.action.phone.UpdAfficeToReadAction">
</action>

<action path="/phone/queryCodeTraceAction" type="com.winsafe.drp.keyretailer.action.phone.QueryCodeTraceAction">
</action>

<action path="/phone/queryRecAndDisSumAction" type="com.winsafe.drp.keyretailer.action.phone.QueryRecAndDisSumAction">
</action>

<action path="/phone/queryRecAndDisSumDetailAction" type="com.winsafe.drp.keyretailer.action.phone.QueryRecAndDisSumDetailAction">
</action>

<action path="/phone/queryCustomerSupportAction" type="com.winsafe.drp.keyretailer.action.phone.QueryCustomerSupportAction">
</action>

<action path="/phone/updCustomerSupportAction" type="com.winsafe.drp.keyretailer.action.phone.UpdCustomerSupportAction">
</action>

<action path="/phone/addOrUpdSBobusTargetAction" type="com.winsafe.drp.keyretailer.action.phone.AddOrUpdSBobusTargetAction">
</action>

<action path="/phone/updOrganAction" type="com.winsafe.drp.keyretailer.action.phone.UpdOrganAction">
</action>

<action path="/phone/queryCustomerAction" type="com.winsafe.drp.keyretailer.action.phone.QueryCustomerAction">
</action>

<action path="/phone/queryCustomerDetailAction" type="com.winsafe.drp.keyretailer.action.phone.QueryCustomerDetailAction">
</action> 

<action path="/phone/querySBobusTargetProductAction" type="com.winsafe.drp.keyretailer.action.phone.QuerySBobusTargetProductAction">
</action>

<action path="/phone/queryBonusConfirmAction" type="com.winsafe.drp.keyretailer.action.phone.QueryBonusConfirmAction">
</action>

<action path="/phone/updBonusConfirmAction" type="com.winsafe.drp.keyretailer.action.phone.UpdBonusConfirmAction">
</action>

<action path="/phone/queryRecAndDisSumProductDetailAction" type="com.winsafe.drp.keyretailer.action.phone.QueryRecAndDisSumProductDetailAction">
</action>

<action path="/phone/queryProductNameAction" type="com.winsafe.drp.keyretailer.action.phone.QueryProductNameAction">
</action>

<action path="/phone/checkVersionAction" type="com.winsafe.drp.keyretailer.action.phone.CheckVersionAction">
</action>

<action path="/phone/querySBobusTargetYearAction" type="com.winsafe.drp.keyretailer.action.phone.QuerySBobusTargetYearAction">
</action>

<action path="/phone/registerNewUser" type="com.winsafe.drp.keyretailer.action.phone.RegisterNewUser">
</action>

<!-- ASM/SS/SR APP -->
<!-- 登陆 -->
<action path="/salesman/userLoginAction" type="com.winsafe.drp.keyretailer.salesman.action.phone.LoginAction">
</action>
<!-- 下载机构信息 -->
<action path="/salesman/queryOrganAction" type="com.winsafe.drp.keyretailer.salesman.action.phone.QueryOrganAction">
</action>
<!-- 用户注册/密码找回 -->
<action path="/salesman/queryNewPassword" type="com.winsafe.drp.keyretailer.salesman.action.phone.QueryNewPasswordAction">
</action>
<!-- BKD/BKR积分查询 -->
<action path="/salesman/queryBonusAction" type="com.winsafe.drp.keyretailer.salesman.action.phone.QueryBonusAction">
</action>
<action path="/salesman/queryBonusDetailAction" type="com.winsafe.drp.keyretailer.salesman.action.phone.QueryBonusDetailAction">
</action> 
<!-- 收发货汇总查询 -->
<action path="/salesman/queryRecAndDisSumAction" type="com.winsafe.drp.keyretailer.salesman.action.phone.QueryRecAndDisSumAction">
</action>
<action path="/salesman/queryRecAndDisSumDetailAction" type="com.winsafe.drp.keyretailer.salesman.action.phone.QueryRecAndDisSumDetailAction">
</action>

<action path="/salesman/updMobileAction" type="com.winsafe.drp.keyretailer.salesman.action.phone.UpdMobileAction">
</action>

<action path="/salesman/updPasswordAction" type="com.winsafe.drp.keyretailer.salesman.action.phone.UpdPasswordAction">
</action>

<action path="/salesman/queryOrganAfficheAction" type="com.winsafe.drp.keyretailer.salesman.action.phone.QueryAfficheAction">
</action>
<action path="/salesman/queryNotReadOrganAfficheAction" type="com.winsafe.drp.keyretailer.salesman.action.phone.QueryNotReadAfficheAction">
</action>
<action path="/salesman/updAfficeToReadAction" type="com.winsafe.drp.keyretailer.salesman.action.phone.UpdAfficeToReadAction">
</action>

<!-- 客户信息确认/审核 -->
<action path="/salesman/queryCustomerToAuditAction" type="com.winsafe.drp.keyretailer.salesman.action.phone.QueryCustomerToAuditAction">
</action>
<action path="/salesman/auditCustomerAction" type="com.winsafe.drp.keyretailer.salesman.action.phone.AuditCustomerAction">
</action>
<action path="/salesman/queryCustomerToAuditCountAction" type="com.winsafe.drp.keyretailer.salesman.action.phone.QueryCustomerToAuditCountAction">
</action>
<!-- 上级进货机构设置  -->
<action path="/salesman/queryTransferOrganToAddAction" type="com.winsafe.drp.keyretailer.salesman.action.phone.QueryTransferOrganToAddAction">
</action>
<action path="/salesman/addTransferRelationAction" type="com.winsafe.drp.keyretailer.salesman.action.phone.AddTransferRelationAction">
</action>

<!-- 客户信息查看 -->
<action path="/salesman/queryCustomerInfoAction" type="com.winsafe.drp.keyretailer.salesman.action.phone.QueryCustomerInfoAction">
</action>

<!-- 客户信息匹配 -->
<action path="/salesman/queryCustomerInfoFromApiAction" type="com.winsafe.drp.keyretailer.salesman.action.phone.QueryCustomerInfoFromApiAction">
</action>

<!-- 返利确认状态查询 -->
<action path="/salesman/queryRebateAction" type="com.winsafe.drp.keyretailer.salesman.action.phone.QueryRebateAction">
</action>

<action path="/salesman/queryProductAction" type="com.winsafe.drp.keyretailer.salesman.action.phone.QueryProductAction">
</action>

<action path="/salesman/getIdentifyCodeAction" type="com.winsafe.drp.keyretailer.salesman.action.phone.GetIdentifyCodeAction">
</action>

<action path="/salesman/queryUsersAction" type="com.winsafe.drp.keyretailer.salesman.action.phone.QueryUsersAction">
</action>

<action path="/salesman/queryBonusListAction" type="com.winsafe.drp.keyretailer.salesman.action.phone.QueryBonusListAction">
</action>

<action path="/salesman/queryBonusProductAction" type="com.winsafe.drp.keyretailer.salesman.action.phone.QueryBonusProductAction">
</action>

<action path="/salesman/queryRecAndDisSumProductDetailAction" type="com.winsafe.drp.keyretailer.salesman.action.phone.QueryRecAndDisSumProductDetailAction">
</action>

<action path="/salesman/queryProductNameAction" type="com.winsafe.drp.keyretailer.salesman.action.phone.QueryProductNameAction">
</action>

<action path="/salesman/checkVersionAction" type="com.winsafe.drp.keyretailer.salesman.action.phone.CheckVersionAction">
</action>
<!-- 转仓单确认/审核 -->
<action path="/salesman/queryStockMoveToAuditAction" type="com.winsafe.drp.keyretailer.salesman.action.phone.QueryStockMoveToAuditAction">
</action>
<action path="/salesman/auditStockMoveAction" type="com.winsafe.drp.keyretailer.salesman.action.phone.AuditStockMoveAction">
</action>
<action path="/salesman/queryStockMoveToAuditCountAction" type="com.winsafe.drp.keyretailer.salesman.action.phone.QueryStockMoveToAuditCountAction">
</action>

<action path="/phone/queryCountryAreaAction" type="com.winsafe.drp.keyretailer.action.phone.QueryCountryAreaAction">
</action>
<action path="/salesman/queryCountryAreaAction" type="com.winsafe.drp.keyretailer.salesman.action.phone.QueryCountryAreaAction">
</action>
<action path="/salesman/queryAreasAction" type="com.winsafe.drp.keyretailer.salesman.action.phone.QueryAreasAction">
</action>

<action path="/salesman/queryUserOrganAction" type="com.winsafe.drp.keyretailer.salesman.action.phone.QueryUserOrganAction">
</action>

<action path="/salesman/queryUsersToAuditAction" type="com.winsafe.drp.keyretailer.salesman.action.phone.QueryUsersToAuditAction">
</action>

<action path="/salesman/auditUserAction" type="com.winsafe.drp.keyretailer.salesman.action.phone.AuditUserAction">
</action>

</action-mappings>
</struts-config>