<?xml version="1.0" encoding="UTF-8"?>
<!DOCTYPE hibernate-mapping PUBLIC "-//Hibernate/Hibernate Mapping DTD 3.0//EN" "http://hibernate.sourceforge.net/hibernate-mapping-3.0.dtd">
<hibernate-mapping>
<class name="com.winsafe.drp.dao.AdjustOIntegralDetail" table="adjust_o_integral_detail">
<id column="ID" name="id" type="java.lang.Long">
<generator class="assigned"/>
</id>
<property column="AOIID" length="32" name="aoiid" type="java.lang.String"/>
<property column="OID" length="32" name="oid" type="java.lang.String"/>
<property column="OName" length="256" name="oname" type="java.lang.String"/>
<property column="AdjustIntegral" length="18" name="adjustintegral" type="java.lang.Double"/>
</class>
</hibernate-mapping>
